TAT.cpython-312-aarch64-linux-musl.so
pytat-0.3.17.dist-info/METADATA
pytat-0.3.17.dist-info/RECORD
pytat-0.3.17.dist-info/WHEEL
pytat.libs/libopenblas_armv8p-r0-df944204.3.25.so
pytat.libs/libgcc_s-7393e603.so.1
pytat.libs/libstdc++-1b614e01.so.6.0.32
pytat.libs/libgfortran-eb933d8e.so.5.0.0
