Metadata-Version: 2.1
Name: PyTAT
Version: 0.3.17
Summary: python binding for TAT(TAT is A Tensor library)
Keywords: tensor,tensor network,tensor network state,PEPS,MPS,quantum many body system
Author-Email: Hao Zhang <zh970205@mail.ustc.edu.cn>
License: GPLv3
Classifier: Development Status :: 4 - Beta
Classifier: Programming Language :: Python :: 3
Classifier: License :: OSI Approved :: GNU General Public License v3 or later (GPLv3+)
Classifier: Topic :: Scientific/Engineering :: Mathematics
Classifier: Topic :: Scientific/Engineering :: Physics
Classifier: Topic :: Software Development :: Libraries :: Python Modules
Project-URL: Homepage, https://github.com/USTC-TNS/TNSP/tree/main/PyTAT
Project-URL: Repository, https://github.com/USTC-TNS/TNSP.git
Project-URL: Issues, https://github.com/USTC-TNS/TNSP/issues
Project-URL: Changelog, https://github.com/USTC-TNS/TNSP/blob/main/CHANGELOG.org
Requires-Dist: numpy
